mf_horizon_client/__init__.py
mf_horizon_client/_version.py
mf_horizon_client/endpoints.py
mf_horizon_client/client/__init__.py
mf_horizon_client/client/error.py
mf_horizon_client/client/horizon_client.py
mf_horizon_client/client/session.py
mf_horizon_client/client/warnings.py
mf_horizon_client/client/datasets/__init__.py
mf_horizon_client/client/datasets/data_interface.py
mf_horizon_client/client/pipelines/__init__.py
mf_horizon_client/client/pipelines/blueprints.py
mf_horizon_client/client/pipelines/construct_pipeline_class.py
mf_horizon_client/client/pipelines/pipeline_interface.py
mf_horizon_client/data_structures/__init__.py
mf_horizon_client/data_structures/column_passport.py
mf_horizon_client/data_structures/dataset_summary.py
mf_horizon_client/data_structures/feature_id.py
mf_horizon_client/data_structures/individual_dataset.py
mf_horizon_client/data_structures/ingestion_process.py
mf_horizon_client/data_structures/pipeline.py
mf_horizon_client/data_structures/pipeline_summary.py
mf_horizon_client/data_structures/predictions.py
mf_horizon_client/data_structures/raw_column.py
mf_horizon_client/data_structures/stage.py
mf_horizon_client/data_structures/configs/__init__.py
mf_horizon_client/data_structures/configs/stage_config.py
mf_horizon_client/data_structures/configs/stage_config_enums.py
mf_horizon_client/data_structures/configs/stage_status.py
mf_horizon_client/data_structures/configs/stage_types.py
mf_horizon_client/post_processing/__init__.py
mf_horizon_client/post_processing/backtests.py
mf_horizon_client/schemas/__init__.py
mf_horizon_client/schemas/configs.py
mf_horizon_client/schemas/schema.py
mf_horizon_client/utils/__init__.py
mf_horizon_client/utils/catch_method_exception.py
mf_horizon_client/utils/progress_bar_helpers.py
mf_horizon_client/utils/string_case_converters.py
mf_horizon_client/utils/terminal_messages.py
mf_horizon_client-2.11.0.dist-info/LICENSE.txt
mf_horizon_client-2.11.0.dist-info/METADATA
mf_horizon_client-2.11.0.dist-info/WHEEL
mf_horizon_client-2.11.0.dist-info/top_level.txt
mf_horizon_client-2.11.0.dist-info/RECORD
